[
  {
    "title": "SMEG30 - Parking Bureau de Poste - Bld Charles Mourier - Bernis",
    "address": "16B Boulevard Charles Mourier - Bernis",
    "connectors": [
      "x2",
      "x2",
      "x2"
    ],
    "types": [
      "Domestique UE",
      "Type 2",
      "Type 3C"
    ],
    "reputation": 1
  },
  {
    "title": "Lidl - Route de Montpellier - Milhaud",
    "address": "1100 Route de Montpellier - Milhaud",
    "connectors": [
      "x4"
    ],
    "types": [
      "Type 2"
    ],
    "reputation": 5
  },
  {
    "title": "SMEG30 (Révéo) - Place Silhol",
    "address": "12 Place Silhol - Aubord",
    "connectors": [
      "x2",
      "x2",
      "x2"
    ],
    "types": [
      "Domestique UE",
      "Type 2",
      "Type 3C"
    ],
    "reputation": 0
  },
  {
    "title": "Révéo - Rond Point rue des Troenes / rue des Tamaris",
    "address": "6 Rue des Troenes - Milhaud",
    "connectors": [
      "x2",
      "x2",
      "x2"
    ],
    "types": [
      "Domestique UE",
      "Type 2",
      "Type 3C"
    ],
    "reputation": 3
  },
  {
    "title": "DRIVECO - Milhaud - Loc +",
    "address": "67 Rte de Nîmes, - Milhaud",
    "connectors": [
      "x1",
      "x2"
    ],
    "types": [
      "Domestique UE",
      "Type 2"
    ],
    "reputation": 0
  },
  {
    "title": "mobilygreen - 3315 Route de Montpellier - Nîmes",
    "address": "3315 Route de Montpellier - Nîmes",
    "connectors": [
      "x2"
    ],
    "types": [
      "Type 2"
    ],
    "reputation": 0
  },
  {
    "title": "SMEG30 (Révéo) - 35 Chemin des Aires - Langlade",
    "address": "35 Chemin des Aires - Langlade",
    "connectors": [
      "x2",
      "x2",
      "x2"
    ],
    "types": [
      "Domestique UE",
      "Type 2",
      "Type 3C"
    ],
    "reputation": 3
  },
  {
    "title": "Chemin des Fumeras Nages-et-Solorgues",
    "address": "Chemin des Fumeras - Nages-et-Solorgues",
    "connectors": [
      "x1"
    ],
    "types": [
      "Type 2"
    ],
    "reputation": 0
  },
  {
    "title": "Volvo - Nîmes - 22kW AC",
    "address": "27 Rue du Pied Ferme - Nîmes",
    "connectors": [
      "x4"
    ],
    "types": [
      "Type 2"
    ],
    "reputation": 0
  },
  {
    "title": "Freshmile - Nîmes - Rue Du Pied Fermé",
    "address": "Rue Du Pied Fermé - Nîmes",
    "connectors": [
      "x1",
      "x2"
    ],
    "types": [
      "Domestique UE",
      "Type 2"
    ],
    "reputation": 0
  }
]