[
  {
    "title": "Grande route - Blangy-le-Château",
    "address": "1 Chemin du Pont Vert - Blangy-le-Château",
    "connectors": [
      "x2",
      "x2"
    ],
    "types": [
      "Domestique UE",
      "Type 2"
    ],
    "reputation": 0
  },
  {
    "title": "Domaine du lac",
    "address": "8 Route du Mesnil - Blangy-le-Château",
    "connectors": [
      "x4"
    ],
    "types": [
      "Domestique UE"
    ],
    "reputation": 0
  },
  {
    "title": "Camping Castel (Tesla et autres)",
    "address": "Château du Brevedent - Le Brévedent",
    "connectors": [
      "x2"
    ],
    "types": [
      "Type 2"
    ],
    "reputation": 0
  },
  {
    "title": "D579 - Fierville les parcs",
    "address": "route de la Vallée de la touques - Fierville les parcs",
    "connectors": [
      "x2",
      "x2"
    ],
    "types": [
      "Domestique UE",
      "Type 2"
    ],
    "reputation": 0
  },
  {
    "title": "MobiSDEC - Norolles (chemin de l'eglise)",
    "address": "220 Chemin de l'Eglise - Norolles",
    "connectors": [
      "x2",
      "x2"
    ],
    "types": [
      "Domestique UE",
      "Type 2"
    ],
    "reputation": 0
  },
  {
    "title": "EVBox - route de Pont Leveque 670 - Saint martin aux chartrains",
    "address": "route de Pont Leveque 670 - Saint martin aux chartrains",
    "connectors": [
      "x4"
    ],
    "types": [
      "Type 2"
    ],
    "reputation": 0
  },
  {
    "title": "MobiSDEC - Bonneville-la-Louvet",
    "address": "2 Place Henri Louvet - Bonneville-la-Louvet",
    "connectors": [
      "x2",
      "x2"
    ],
    "types": [
      "Domestique UE",
      "Type 2"
    ],
    "reputation": 5
  },
  {
    "title": "Eden Park - Route du Parc",
    "address": "Route du Lac - Pont-l'Évêque",
    "connectors": [
      "x2"
    ],
    "types": [
      "Type 2"
    ],
    "reputation": 0
  },
  {
    "title": "Villa nouveau monde - Bonneville la louvet",
    "address": "517 Route de cormeilles - Bonneville la louvet",
    "connectors": [
      "x1"
    ],
    "types": [
      "Domestique UE"
    ],
    "reputation": 0
  },
  {
    "title": "MobiSDEC - Coquainvilliers - Rue du Manoir de Prie",
    "address": "1 D48 - Coquainvilliers",
    "connectors": [
      "x2",
      "x2"
    ],
    "types": [
      "Domestique UE",
      "Type 2"
    ],
    "reputation": 0
  }
]