[
  {
    "title": "SEYMABORNE - Rue du Général Leclerc - Chanteloup-les-Vignes",
    "address": "Rue du Général Leclerc - Chanteloup-les-Vignes",
    "connectors": [
      "x2"
    ],
    "types": [
      "Type 2"
    ],
    "reputation": 4
  },
  {
    "title": "SEYMABORNE - Chanteloup les Vignes",
    "address": "8 Rue d'Andrésy - Chanteloup-les-Vignes",
    "connectors": [
      "x2",
      "x2"
    ],
    "types": [
      "Domestique UE",
      "Type 2"
    ],
    "reputation": 5
  },
  {
    "title": "ALDI Chanteloup-les-Vignes",
    "address": "104 Rue d'Alentours - Chanteloup-les-Vignes",
    "connectors": [
      "x4"
    ],
    "types": [
      "Type 2"
    ],
    "reputation": 0
  },
  {
    "title": "SEYMABORNE - Place de la Gare - Andrésy",
    "address": "Place de la Gare - Andrésy",
    "connectors": [
      "x2",
      "x2"
    ],
    "types": [
      "Domestique UE",
      "Type 2"
    ],
    "reputation": 5
  },
  {
    "title": "SEYMABORNE - Andrésy - 12 Sentier des Garennes",
    "address": "12 Sentier des Garennes - Andrésy",
    "connectors": [
      "x2"
    ],
    "types": [
      "Type 2"
    ],
    "reputation": 3.5
  },
  {
    "title": "SEYMABORNE- Parking de la Gare de Triel sur Seine",
    "address": "45 Rue du Docteur Sobaux - Triel-sur-Seine",
    "connectors": [
      "x1",
      "x1"
    ],
    "types": [
      "Type 3C",
      "Type 2"
    ],
    "reputation": 3
  },
  {
    "title": "NW IECharge - 1 Avenue de Poissy - Triel-sur-Seine",
    "address": "1 Avenue de Poissy - Triel-sur-Seine",
    "connectors": [
      "x2",
      "x2"
    ],
    "types": [
      "Combo CSS",
      "Combo CSS"
    ],
    "reputation": 3
  },
  {
    "title": "Electricité Seine Aval - Bords de Seine - Boulevard Noël Marc Andrésy",
    "address": "40 Boulevard Noël Marc - Andrésy",
    "connectors": [
      "x1",
      "x1"
    ],
    "types": [
      "Type 3C",
      "Type 2"
    ],
    "reputation": 5
  },
  {
    "title": "SEYMABORNE - Mairie de Triel",
    "address": "190 Rue Paul Doumer - Triel-sur-Seine",
    "connectors": [
      "x1",
      "x1"
    ],
    "types": [
      "Type 3C",
      "Type 2"
    ],
    "reputation": 0
  },
  {
    "title": "Hesion - Achères (privé)",
    "address": "1 Allée de la Rhubarbe - Achères",
    "connectors": [
      "x1"
    ],
    "types": [
      "Type 2"
    ],
    "reputation": 0
  }
]