[
  {
    "title": "Pass Pass - Mairie de Courchelettes",
    "address": "1 Rue Emile Macra - Courchelettes",
    "connectors": [
      "x2",
      "x2"
    ],
    "types": [
      "Domestique UE",
      "Type 2"
    ],
    "reputation": 5
  },
  {
    "title": "R3 - Rue Jean Monnet - Brebieres",
    "address": "1\r\n Rue Jean Monnet\r\n - Brebières",
    "connectors": [
      "x2",
      "x2",
      "x1",
      "x1",
      "x2"
    ],
    "types": [
      "Type 2",
      "Combo CSS",
      "Combo CSS",
      "CHAdeMO",
      "Type 2"
    ],
    "reputation": 0
  },
  {
    "title": "Pass-Pass - Lambres-Lez-Douai",
    "address": "397 Rue des frères Bréguet - Lambres-Lez-Douai",
    "connectors": [
      "x1",
      "x1",
      "x1"
    ],
    "types": [
      "Type 2",
      "CHAdeMO",
      "Combo CSS"
    ],
    "reputation": 3
  },
  {
    "title": "Pass Pass - Lambres-lez-Douai - Mairie",
    "address": "269-291 Rue Jean Jaurès - Lambres-Lez-Douai",
    "connectors": [
      "x2",
      "x2"
    ],
    "types": [
      "Type 2",
      "Domestique UE"
    ],
    "reputation": 0
  },
  {
    "title": "FR*H04 - Lambres-Lez-Douai - 593 Rue Gallieni",
    "address": "593 Rue Gallieni - Lambres-Lez-Douai",
    "connectors": [
      "x2"
    ],
    "types": [
      "Type 2"
    ],
    "reputation": 0
  },
  {
    "title": "E-Totem - Férin - Silver Wash Auto",
    "address": "40 Route Nationale - Férin",
    "connectors": [
      "x1",
      "x1",
      "x2",
      "x2"
    ],
    "types": [
      "Domestique UE",
      "Type 2",
      "Combo CSS",
      "Combo CSS"
    ],
    "reputation": 4
  },
  {
    "title": "Renault - Brebieres",
    "address": "Rue de Vitry - Brebières",
    "connectors": [
      "x1"
    ],
    "types": [
      "Type 3C"
    ],
    "reputation": 0
  },
  {
    "title": "Le Comptoir du Malt",
    "address": "1911 Route de Dechy - Férin",
    "connectors": [
      "x2",
      "x2"
    ],
    "types": [
      "Type 2",
      "Domestique UE"
    ],
    "reputation": 0
  },
  {
    "title": "Shell Recharge - Bricodepot - Férin",
    "address": "3 Route de Cambrai - Férin",
    "connectors": [
      "x12",
      "x12"
    ],
    "types": [
      "Domestique UE",
      "Type 2"
    ],
    "reputation": 3
  },
  {
    "title": "Auchan - Rocade Est - Douai Sin-le-Noble",
    "address": "D25 Route nationale - Sin-le-Noble",
    "connectors": [
      "x2",
      "x1"
    ],
    "types": [
      "Type 2",
      "Domestique UE"
    ],
    "reputation": 1
  }
]