[
  {
    "title": "Vauclus'Elec (SEV84) - Vieille Route d'Apt - RUSTREL",
    "address": "5000 Le Petit Plan Du Grand Jas - Rustrel",
    "connectors": [
      "x1",
      "x2",
      "x2"
    ],
    "types": [
      "Domestique UE",
      "Domestique UE",
      "Type 2"
    ],
    "reputation": 4.5
  },
  {
    "title": "Vauclus'Elec (SEV84) - Saint Christol - Chemin des Eglantiers (Chemin de Ronde)",
    "address": "1 Chemin de Ronde - Saint-Christol",
    "connectors": [
      "x2",
      "x2"
    ],
    "types": [
      "Domestique UE",
      "Type 2"
    ],
    "reputation": 1
  },
  {
    "title": "Hameau Le Bosquet, Saint-Christol INEXISTANT",
    "address": "360 hameau Le Bosquet - Saint-Christol",
    "connectors": [
      "x1",
      "x1"
    ],
    "types": [
      "Domestique UE",
      "Type 2"
    ],
    "reputation": 0
  },
  {
    "title": "Les Davids",
    "address": "1 Rue ambroize - Viens",
    "connectors": [],
    "types": [],
    "reputation": 0
  },
  {
    "title": "SDE04 - Place de la poste - Banon",
    "address": "Le Village - Banon",
    "connectors": [
      "x2",
      "x2"
    ],
    "types": [
      "Domestique UE",
      "Type 2"
    ],
    "reputation": 4
  },
  {
    "title": "SDE04 - Avenue de Miravail",
    "address": "7092 Avenue de Miravail - Revest-du-Bion",
    "connectors": [
      "x2",
      "x2"
    ],
    "types": [
      "Domestique UE",
      "Type 2"
    ],
    "reputation": 5
  },
  {
    "title": "Vauclus'Elec (SEV84) - Saint Saturnin les Apt - Chemin de la Bruyère",
    "address": "88 Chemin de la Bruyère - Saint-Saturnin-lès-Apt",
    "connectors": [
      "x4",
      "x4"
    ],
    "types": [
      "Domestique UE",
      "Type 2"
    ],
    "reputation": 4
  },
  {
    "title": "SDE04 - Place des Aires",
    "address": "3 Rue Jean Mermoz - Céreste",
    "connectors": [
      "x2",
      "x2"
    ],
    "types": [
      "Domestique UE",
      "Type 2"
    ],
    "reputation": 5
  },
  {
    "title": "Hotel Castel Luberon - Apt",
    "address": "1526 Avenue de Viton - Apt",
    "connectors": [
      "x1"
    ],
    "types": [
      "Domestique UE"
    ],
    "reputation": 0
  },
  {
    "title": "Domaine des Andéols (Tesla and others)",
    "address": "Les Andéols - Saint-Saturnin-lès-Apt",
    "connectors": [
      "x3"
    ],
    "types": [
      "Type 2"
    ],
    "reputation": 0
  }
]