[
  {
    "title": "SDEF - Querrien (Place de l'Eglise)",
    "address": "1P Place de l'Église - Querrien",
    "connectors": [
      "x1",
      "x3"
    ],
    "types": [
      "Domestique UE",
      "Type 2"
    ],
    "reputation": 0
  },
  {
    "title": "Morbihan énergies - Cours Carré - Le Faouët",
    "address": "Cours Carré - Le Faouët",
    "connectors": [
      "x2",
      "x2"
    ],
    "types": [
      "Domestique UE",
      "Type 2"
    ],
    "reputation": 4.5
  },
  {
    "title": "SDEF - Saint Thurien (Place Kilmacow)",
    "address": "9 Rue de Quimperlé - Saint-Thurien",
    "connectors": [
      "x2"
    ],
    "types": [
      "Type 2"
    ],
    "reputation": 5
  },
  {
    "title": "Morbihan énergies - Rue de la Butte - Meslan",
    "address": "Rue Joseph le Gallo - Meslan",
    "connectors": [
      "x2",
      "x2"
    ],
    "types": [
      "Domestique UE",
      "Type 2"
    ],
    "reputation": 4
  },
  {
    "title": "Parc Aquanature du Sterou",
    "address": "Le Pleno - Priziac",
    "connectors": [
      "x1"
    ],
    "types": [
      "Domestique UE"
    ],
    "reputation": 0
  },
  {
    "title": "SDEF - Locunolé (Mairie)",
    "address": "2 Rue de Beg ar Roz - Locunolé",
    "connectors": [
      "x2"
    ],
    "types": [
      "Type 2"
    ],
    "reputation": 0
  },
  {
    "title": "Freshmile (FR*S56) - Guiscriff - Place centrale",
    "address": "Place centrale - Guiscriff",
    "connectors": [
      "x2",
      "x2"
    ],
    "types": [
      "Domestique UE",
      "Type 2"
    ],
    "reputation": 4
  },
  {
    "title": "SDEF - Rue du Faouët - Tréméven",
    "address": "46 Rue du Faouët - Tréméven",
    "connectors": [
      "x2"
    ],
    "types": [
      "Type 2"
    ],
    "reputation": 0
  },
  {
    "title": "Morbihan énergie - Place de la Mairie - Berné",
    "address": "Place de la Mairie - Berné",
    "connectors": [
      "x2",
      "x2"
    ],
    "types": [
      "Domestique UE",
      "Type 2"
    ],
    "reputation": 4
  },
  {
    "title": "SDEF - Mellac (Ty Bodel)",
    "address": "Pôle d'activité Kervidanou - Mellac",
    "connectors": [
      "x2"
    ],
    "types": [
      "Type 2"
    ],
    "reputation": 0
  }
]