[
  {
    "title": "SIEGE27 - Boisement / Saint Jean de Frenelles",
    "address": "26 Route de Rouen - Corny",
    "connectors": [
      "x2",
      "x2"
    ],
    "types": [
      "Domestique UE",
      "Type 2"
    ],
    "reputation": 4
  },
  {
    "title": "Lidl - Ecouis",
    "address": "5000 Rue Nationale - Écouis",
    "connectors": [
      "x1",
      "x1",
      "x2",
      "x2",
      "x1",
      "x1"
    ],
    "types": [
      "Combo CSS",
      "Combo CSS",
      "Combo CSS",
      "CHAdeMO",
      "Type 2",
      "Type 2"
    ],
    "reputation": 4
  },
  {
    "title": "Menuiserie Lempereur",
    "address": "Route de Frileuse - Longchamps",
    "connectors": [
      "x1"
    ],
    "types": [
      "Type 3C"
    ],
    "reputation": 0
  },
  {
    "title": "SIEGE27 - Étrépagny",
    "address": "22 Rue Maison De Vatimesnil - Étrépagny",
    "connectors": [
      "x2",
      "x2"
    ],
    "types": [
      "Type 2",
      "Domestique UE"
    ],
    "reputation": 5
  },
  {
    "title": "Freshmile - Rosay-sur-Lieure - Route De Lyons",
    "address": "Route De Lyons - Rosay-sur-Lieure",
    "connectors": [
      "x2",
      "x4"
    ],
    "types": [
      "Domestique UE",
      "Type 2"
    ],
    "reputation": 5
  },
  {
    "title": "Hotel la Licorne",
    "address": "Rue du Trou Grenu - Lyons-la-Forêt",
    "connectors": [
      "x1"
    ],
    "types": [
      "Domestique UE"
    ],
    "reputation": 0
  },
  {
    "title": "SIEGE27 - Lyons-la-Forêt",
    "address": "1 Rue du Four À Chaux - Lyons-la-Forêt",
    "connectors": [
      "x2",
      "x2"
    ],
    "types": [
      "Domestique UE",
      "Type 2"
    ],
    "reputation": 5
  },
  {
    "title": "Intermarché - Les Andelys",
    "address": "11 Clos du Gambon - Les Andelys",
    "connectors": [
      "x6"
    ],
    "types": [
      "Type 2"
    ],
    "reputation": 0
  },
  {
    "title": "SGA - Avenue du Gén de Gaulle",
    "address": "24 Avenue du Gén de Gaulle - Les Andelys",
    "connectors": [
      "x2",
      "x2"
    ],
    "types": [
      "Domestique UE",
      "Type 2"
    ],
    "reputation": 0
  },
  {
    "title": "Siège 27 - Place Nicolas Poussin",
    "address": "24 Place Nicolas Poussin - Les Andelys",
    "connectors": [
      "x2",
      "x2"
    ],
    "types": [
      "Domestique UE",
      "Type 2"
    ],
    "reputation": 0
  }
]