[
  {
    "title": "EVBox - Route de Servas 2958 - Condeissiat",
    "address": "Route de Servas 2958 - Condeissiat",
    "connectors": [
      "x4"
    ],
    "types": [
      "Type 2"
    ],
    "reputation": 0
  },
  {
    "title": "ChargePoint network - 2111 Route de Châtillon - Romans",
    "address": "2111 Route de Châtillon - Romans",
    "connectors": [
      "x4"
    ],
    "types": [
      "Type 2"
    ],
    "reputation": 0
  },
  {
    "title": "Powerdot - Servas - Intermarché",
    "address": "ZA du Val Roman, Route de Lyon, - Servas",
    "connectors": [
      "x1",
      "x1",
      "x1",
      "x2"
    ],
    "types": [
      "Type 2",
      "CHAdeMO",
      "Combo CSS",
      "Combo CSS"
    ],
    "reputation": 3.5
  },
  {
    "title": "camping domaine de la dombe",
    "address": "1 chemin de verfey - Saint-Paul-de-Varax",
    "connectors": [],
    "types": [],
    "reputation": 0
  },
  {
    "title": "WAAT - Neuville-les-Dames - 139 Allée Jean Brevet",
    "address": "139 Allée Jean Brevet - Neuville-les-Dames",
    "connectors": [
      "x2"
    ],
    "types": [
      "Type 2"
    ],
    "reputation": 0
  },
  {
    "title": "Intermarche - Châtillon-sur-Chalaronne",
    "address": "481 Avenue Jean Jaurès - Châtillon sur Chalaronne",
    "connectors": [
      "x2",
      "x2"
    ],
    "types": [
      "Domestique UE",
      "Type 2"
    ],
    "reputation": 0
  },
  {
    "title": "236 Impasse du Moulin de Longchamp",
    "address": "236 Impasse du Moulin de Longchamp - Lent",
    "connectors": [
      "x1"
    ],
    "types": [
      "Type 2"
    ],
    "reputation": 0
  },
  {
    "title": "Le moulin de Lonchamp",
    "address": "236 Impasse du Moulin dd Longchamp - Le t",
    "connectors": [
      "x1"
    ],
    "types": [
      "Type 2"
    ],
    "reputation": 0
  },
  {
    "title": "Izivia - Place du champ de foire - Châtillon-sur-Chalaronne",
    "address": "100 Place du Champ de Foire - Châtillon-sur-Chalaronne",
    "connectors": [
      "x2",
      "x2"
    ],
    "types": [
      "Domestique UE",
      "Type 2"
    ],
    "reputation": 3.5
  },
  {
    "title": "Route de Saint triviers - Sandrans",
    "address": "10 Lotissement le Pré Chapon - Sandrans",
    "connectors": [
      "x2",
      "x2"
    ],
    "types": [
      "Domestique UE",
      "Type 2"
    ],
    "reputation": 0
  }
]