[
  {
    "title": "château de boistissandeau",
    "address": "Unnamed Road - Les Herbiers",
    "connectors": [
      "x1"
    ],
    "types": [
      "Type 2"
    ],
    "reputation": 0
  },
  {
    "title": "Freshmile - Leclerc - Les Herbiers",
    "address": "Unnamed Road - Les Herbiers",
    "connectors": [
      "x4",
      "x4"
    ],
    "types": [
      "Domestique UE",
      "Type 2"
    ],
    "reputation": 4.5
  },
  {
    "title": "SyDEV - Rue du Baron Pierre de Coubertin - Les Herbiers",
    "address": "2 Rue Raymond Kopa - Les Herbiers",
    "connectors": [
      "x2",
      "x2"
    ],
    "types": [
      "Domestique UE",
      "Type 2"
    ],
    "reputation": 3
  },
  {
    "title": "Le Grand Fief (Privé)",
    "address": "Le Grand Fief - Les Herbiers",
    "connectors": [
      "x2"
    ],
    "types": [
      "Type 2"
    ],
    "reputation": 0
  },
  {
    "title": "Sydev - Rue des Arts - Les Herbiers",
    "address": "529 Place d'Herbauges - Les Herbiers",
    "connectors": [
      "x2",
      "x2"
    ],
    "types": [
      "Domestique UE",
      "Type 2"
    ],
    "reputation": 5
  },
  {
    "title": "Electromaps S.L./7038",
    "address": "3 Rue du Château Gaillard - Les Herbiers",
    "connectors": [
      "x2"
    ],
    "types": [
      "Type 2"
    ],
    "reputation": 0
  },
  {
    "title": "SyDEV - Place du Champ de Foire - Les Herbiers",
    "address": "Place du Champ de Foire - Les Herbiers",
    "connectors": [
      "x2",
      "x2"
    ],
    "types": [
      "Domestique UE",
      "Type 2"
    ],
    "reputation": 4
  },
  {
    "title": "Lidl - Les Herbiers",
    "address": "Rue du Grand Rouet - Les Herbiers",
    "connectors": [
      "x2"
    ],
    "types": [
      "Type 2"
    ],
    "reputation": 4.5
  },
  {
    "title": "Izivia - Hyper U - Les Herbiers",
    "address": "4 Avenue de la Maine - Les Herbiers",
    "connectors": [
      "x8",
      "x8"
    ],
    "types": [
      "Domestique UE",
      "Type 2"
    ],
    "reputation": 4.5
  },
  {
    "title": "Freshmile - Buffalo Grill - les Herbiers",
    "address": "68 Avenue de la maine - Les herbiers",
    "connectors": [
      "x2",
      "x2"
    ],
    "types": [
      "Domestique UE",
      "Type 2"
    ],
    "reputation": 0
  }
]