[
  {
    "title": "SDEHG - Massabrac, Mairie",
    "address": "20 - Massabrac",
    "connectors": [
      "x2",
      "x2"
    ],
    "types": [
      "Domestique UE",
      "Type 2"
    ],
    "reputation": 0
  },
  {
    "title": "SDE09 - Avenue des Moulins",
    "address": "2 Avenue des Moulins - Lézat-sur-Lèze",
    "connectors": [
      "x2",
      "x2"
    ],
    "types": [
      "Domestique UE",
      "Type 2"
    ],
    "reputation": 5
  },
  {
    "title": "Boulodrome - Lézat-sur-Lèze",
    "address": "48 Boulevard Pasteur - Lézat-sur-Lèze",
    "connectors": [
      "x2",
      "x2"
    ],
    "types": [
      "Domestique UE",
      "Type 2"
    ],
    "reputation": 0
  },
  {
    "title": "SDE09 - Place du Foirail Le Fossat",
    "address": "1 Place du Foirail - Le Fossat",
    "connectors": [
      "x2",
      "x2"
    ],
    "types": [
      "Domestique UE",
      "Type 2"
    ],
    "reputation": 4
  },
  {
    "title": "SDEHG - Saint-Sulpice-sur-Lèze, Gendarmerie",
    "address": "1 rue Étienne Fonfrede - Saint-Sulpice-sur-Lèze",
    "connectors": [
      "x2",
      "x2"
    ],
    "types": [
      "Domestique UE",
      "Type 2"
    ],
    "reputation": 1
  },
  {
    "title": "SDE09 - Avenue de la Guinguette Daumazan-sur-Arize",
    "address": "18 Avenue de la Guinguette - Daumazan-sur-Arize",
    "connectors": [
      "x2",
      "x2"
    ],
    "types": [
      "Domestique UE",
      "Type 2"
    ],
    "reputation": 5
  },
  {
    "title": "SDEHG - Montesquieu-Volvestre, Esplanade Nord",
    "address": "19 Esplanade Nord - Montesquieu-Volvestre",
    "connectors": [
      "x2",
      "x2"
    ],
    "types": [
      "Domestique UE",
      "Type 2"
    ],
    "reputation": 5
  },
  {
    "title": "SDEHG - Auribail, Cimetière",
    "address": "51 Le Moulin - Auribail",
    "connectors": [
      "x2",
      "x2"
    ],
    "types": [
      "Domestique UE",
      "Type 2"
    ],
    "reputation": 0
  },
  {
    "title": "Shell Recharge - 1365 D820, Route Nationale Vingt - Cintegabelle",
    "address": "1365 D820, Route Nationale Vingt - Cintegabelle",
    "connectors": [
      "x1"
    ],
    "types": [
      "Type 2"
    ],
    "reputation": 0
  },
  {
    "title": "SDEHG - Carbonne - Office de tourisme",
    "address": "19 Place de la République - Carbonne",
    "connectors": [
      "x2",
      "x2"
    ],
    "types": [
      "Domestique UE",
      "Type 2"
    ],
    "reputation": 4
  }
]