[
  {
    "title": "e-born - Rue de l'Hôtel de Ville - Nivolas-Vermelle",
    "address": "85 Rue Jean Moulin - Nivolas-Vermelle",
    "connectors": [
      "x2",
      "x2"
    ],
    "types": [
      "Domestique UE",
      "Type 2"
    ],
    "reputation": 3
  },
  {
    "title": "Symp Hôtel - Route Nationale 85",
    "address": "1941 Route Nationale 85 - Nivolas-Vermelle",
    "connectors": [
      "x1"
    ],
    "types": [
      "Domestique UE"
    ],
    "reputation": 0
  },
  {
    "title": "SEDI - Passage des Papeteries - Saint-Victor-de-Cessieu",
    "address": "60 Passage des Papeteries - Saint-Victor-de-Cessieu",
    "connectors": [
      "x2",
      "x2"
    ],
    "types": [
      "Domestique UE",
      "Type 2"
    ],
    "reputation": 4
  },
  {
    "title": "SEDI - Rue Des Grands Tournants - Meyrié",
    "address": "Chemin les Grands Tournants - Meyrié",
    "connectors": [
      "x2",
      "x2"
    ],
    "types": [
      "Domestique UE",
      "Type 2"
    ],
    "reputation": 4
  },
  {
    "title": "Dauphiné Poids Lourds",
    "address": "121 rue du lac - Nivolas-Vermelle",
    "connectors": [
      "x1",
      "x1"
    ],
    "types": [
      "Combo CSS",
      "Type 2"
    ],
    "reputation": 0
  },
  {
    "title": "SEDI - Parking Chemin De L Usine - Biol",
    "address": "Impasse de la Galerie - Biol",
    "connectors": [
      "x2",
      "x2"
    ],
    "types": [
      "Domestique UE",
      "Type 2"
    ],
    "reputation": 0
  },
  {
    "title": "VAIRAI TP - Saint-Victor-de-Cessieu",
    "address": "1126 Route de Doissin - Saint-Victor-de-Cessieu",
    "connectors": [
      "x1"
    ],
    "types": [
      "Type 3C"
    ],
    "reputation": 4
  },
  {
    "title": "Izivia - 1320 Route de Doissin - Saint-Victor-de-Cessieu",
    "address": "1320 Route de Doissin - Saint-Victor-de-Cessieu",
    "connectors": [
      "x1",
      "x1"
    ],
    "types": [
      "Domestique UE",
      "Type 2"
    ],
    "reputation": 0
  },
  {
    "title": "Freshmile - Ruy-Montceau - Domaine des Séquoias",
    "address": "190 Route De Boussieu - Ruy-Montceau",
    "connectors": [
      "x6",
      "x6"
    ],
    "types": [
      "Domestique UE",
      "Type 2"
    ],
    "reputation": 0
  },
  {
    "title": "Freshmile - Renault - 3 Chemin Du Poulard - Montrevel",
    "address": "3 Chemin Du Poulard - Montrevel",
    "connectors": [
      "x1",
      "x1"
    ],
    "types": [
      "Domestique UE",
      "Type 2"
    ],
    "reputation": 0
  }
]