[
  {
    "title": "SDE07 (e-born) - Pessade - Cros-de-Géorand",
    "address": "Pessade - Cros-de-Géorand",
    "connectors": [
      "x2",
      "x2"
    ],
    "types": [
      "Domestique UE",
      "Type 2"
    ],
    "reputation": 0
  },
  {
    "title": "SDE07 - Le village - Sainte-Eulalie",
    "address": "D116 - Sainte-Eulalie",
    "connectors": [
      "x2",
      "x2"
    ],
    "types": [
      "Domestique UE",
      "Type 2"
    ],
    "reputation": 0
  },
  {
    "title": "SDE07 - Les Sagnes Sagnes-et-Goudoulet",
    "address": "Les Sagnes - Sagnes-et-Goudoulet",
    "connectors": [
      "x2",
      "x2"
    ],
    "types": [
      "Domestique UE",
      "Type 2"
    ],
    "reputation": 4
  },
  {
    "title": "Bar la cigale",
    "address": "14 Grand Rue - Burzet",
    "connectors": [
      "x1",
      "x1"
    ],
    "types": [
      "Type 2",
      "Domestique UE"
    ],
    "reputation": 0
  },
  {
    "title": "SDE07 - Place de la Paix Montpezat-Sous-Bauzon",
    "address": "2 Place de la Paix - Montpezat-Sous-Bauzon",
    "connectors": [
      "x2",
      "x2"
    ],
    "types": [
      "Domestique UE",
      "Type 2"
    ],
    "reputation": 2
  },
  {
    "title": "SDE07 - Le Village - Le Lac-d'Issarlès",
    "address": "Le Village - Le Lac-d'Issarlès",
    "connectors": [
      "x2",
      "x2"
    ],
    "types": [
      "Domestique UE",
      "Type 2"
    ],
    "reputation": 4
  },
  {
    "title": "SDE07 - Place du Champ de Mars",
    "address": "Place du Champ de Mars - Thueyts",
    "connectors": [
      "x2",
      "x2"
    ],
    "types": [
      "Domestique UE",
      "Type 2"
    ],
    "reputation": 4
  },
  {
    "title": "eborn - Place du Chambon - Mayres",
    "address": "Place du Chambon - Mayres",
    "connectors": [
      "x1",
      "x1",
      "x1"
    ],
    "types": [
      "Type 2",
      "CHAdeMO",
      "Combo CSS"
    ],
    "reputation": 4.5
  },
  {
    "title": "SDE07 - N 102 - Lanarce",
    "address": "N 102 - Lanarce",
    "connectors": [
      "x2",
      "x2"
    ],
    "types": [
      "Domestique UE",
      "Type 2"
    ],
    "reputation": 5
  },
  {
    "title": "SDE07 - Place du Champ de Mars Meyras",
    "address": "Place du Champ de Mars - Meyras",
    "connectors": [
      "x2",
      "x2"
    ],
    "types": [
      "Domestique UE",
      "Type 2"
    ],
    "reputation": 5
  }
]